s_f/__init__.py
s_f/ExampleAgent.py
s_f-0.0.1.dev2.dist-info/METADATA
s_f-0.0.1.dev2.dist-info/WHEEL
s_f-0.0.1.dev2.dist-info/RECORD
